anothermodule/__init__.py
anothermodule/text.txt
flchat/__init__.py
flchat/__main__.py
flchat/config.py
flchat/module.py
flchat/utils.py
flchat/assets/static/all.css
flchat/assets/static/bootstrap.min.css
flchat/assets/static/bootstrap.min.css.map
flchat/assets/static/icon-ai.ico
flchat/assets/static/icon-ai.png
flchat/assets/static/icon-user.png
flchat/assets/static/jquery-3.3.1.min.js
flchat/assets/static/logo-ai.svg
flchat/assets/static/style.css
flchat/assets/templates/chat.html
flchat/assets/templates/index.html
flchat/submodule/__init__.py
flchat-0.0.0.dist-info/LICENSE.txt
flchat-0.0.0.dist-info/METADATA
flchat-0.0.0.dist-info/WHEEL
flchat-0.0.0.dist-info/entry_points.txt
flchat-0.0.0.dist-info/top_level.txt
flchat-0.0.0.dist-info/RECORD
